excel2sbol/__init__.py
excel2sbol/comp_column_functions2.py
excel2sbol/compiler.py
excel2sbol/converter.py
excel2sbol/helpers.py
excel2sbol/library2.py
excel2sbol/library3.py
excel2sbol/lookup_compiler.py
excel2sbol-1.1.18.dist-info/licenses/LICENSE
excel2sbol-1.1.18.dist-info/METADATA
excel2sbol-1.1.18.dist-info/WHEEL
excel2sbol-1.1.18.dist-info/top_level.txt
excel2sbol-1.1.18.dist-info/RECORD
