Metadata-Version: 2.4
Name: excel2sbol
Version: 1.1.18
Summary: Excel-to-SBOL is an open source python library that converts Excel Templates to SBOL documents
Author-email: Jet Mante <jet.mante@colorado.edu>
Maintainer-email: Carolus Vitalis <carolus.vitalis@colorado.edu>
License-Expression: BSD-3-Clause
Project-URL: Homepage, https://github.com/SynBioDex/Excel-to-SBOL
Project-URL: Bug Tracker, https://github.com/SynBioDex/Excel-to-SBOL/issues
Keywords: SBOL,Excel,templates,convert,synthetic biology
Classifier: Programming Language :: Python :: 3
Classifier: Operating System :: OS Independent
Requires-Python: >=3.9
License-File: LICENSE
Requires-Dist: openpyxl==3.0.7
Requires-Dist: numpy==1.26.2
Requires-Dist: pandas==1.5.3
Requires-Dist: rdflib==6.2
Requires-Dist: requests==2.25.1
Requires-Dist: sbol2==1.4
Requires-Dist: sbol3==1.1
Requires-Dist: tyto==1.4
Requires-Dist: urllib3==1.26.5
Requires-Dist: validators==0.18.2
Provides-Extra: test
Requires-Dist: pytest<5.0.0; extra == "test"
Requires-Dist: pytest-cov[all]; extra == "test"
Dynamic: license-file
